pocketbase/__init__.py
pocketbase/client.py
pocketbase/collection.py
pocketbase/errors.py
pocketbase_client-0.2.3.dist-info/WHEEL
pocketbase_client-0.2.3.dist-info/METADATA
pocketbase_client-0.2.3.dist-info/RECORD
